MANIFEST.in
Package.bat
requirements.txt
setup.py
.idea/CodeLibWrapper.iml
.idea/codeStyleSettings.xml
.idea/encodings.xml
.idea/misc.xml
.idea/modules.xml
.idea/vagrant.xml
.idea/vcs.xml
.idea/dictionaries/bzhou.xml
.idea/inspectionProfiles/Project_Default.xml
.idea/inspectionProfiles/profiles_settings.xml
CodeLibWrapper/CodeLibWrapper.py
CodeLibWrapper/CodeLibWrapper.pyc
CodeLibWrapper/License.txt
CodeLibWrapper/README.txt
CodeLibWrapper/Uninstall.bat
CodeLibWrapper/Upgrade.bat
CodeLibWrapper/__init__.py
CodeLibWrapper/__init__.pyc
CodeLibWrapper.egg-info/PKG-INFO
CodeLibWrapper.egg-info/SOURCES.txt
CodeLibWrapper.egg-info/dependency_links.txt
CodeLibWrapper.egg-info/requires.txt
CodeLibWrapper.egg-info/top_level.txt
CodeLibWrapper/API/APIReader.py
CodeLibWrapper/API/APIReader.pyc
CodeLibWrapper/API/__init__.py
CodeLibWrapper/API/__init__.pyc
CodeLibWrapper/BuildInLibs/OS_Path.py
CodeLibWrapper/BuildInLibs/__init__.py
CodeLibWrapper/Collection/CollectionHelper.py
CodeLibWrapper/Collection/__init__.py
CodeLibWrapper/DataAnalysis/DeepDiffUtils.py
CodeLibWrapper/DataAnalysis/__init__.py
CodeLibWrapper/DataAnalysis/__init__.pyc
CodeLibWrapper/Database/DummyCursor.py
CodeLibWrapper/Database/InformaticaHelper.py
CodeLibWrapper/Database/MySQLHelper.py
CodeLibWrapper/Database/SQLServerHelper.py
CodeLibWrapper/Database/SQLServerHelper.pyc
CodeLibWrapper/Database/SQLServerWithBloomFilter.py
CodeLibWrapper/Database/SQLiteHelper.py
CodeLibWrapper/Database/__init__.py
CodeLibWrapper/Database/__init__.pyc
CodeLibWrapper/Database/dvff.py
CodeLibWrapper/FileFormat/CSVHelper.py
CodeLibWrapper/FileFormat/Excel.py
CodeLibWrapper/FileFormat/JmeterReportConvert.py
CodeLibWrapper/FileFormat/JsonUtils.py
CodeLibWrapper/FileFormat/__init__.py
CodeLibWrapper/FileFormat/xml2json.py
CodeLibWrapper/IO/CompareUtils.py
CodeLibWrapper/IO/FileHelper.py
CodeLibWrapper/IO/FileTraversal.py
CodeLibWrapper/IO/FolderCompare.py
CodeLibWrapper/IO/ReadTxtFile.py
CodeLibWrapper/IO/SimpleFileCompare.py
CodeLibWrapper/IO/SimpleFileCompare.pyc
CodeLibWrapper/IO/ZipFileHelper.py
CodeLibWrapper/IO/__init__.py
CodeLibWrapper/IO/__init__.pyc
CodeLibWrapper/MathUtils/MathUtils.py
