Metadata-Version: 1.0
Name: CodeLibWrapper
Version: 0.1.34
Summary: Robot Framework util package for MorningStar DataProduct/API team.
Home-page: https://pypi.python.org/pypi/CodeLibWrapper
Author: Benjamin Zhou
Author-email: Benjamin.Zhou@morningstar.com
License: All Data Production/API QA team member use.
Keywords: Data Production,API,Robot Framework
Platform: Python & Robot framework
